Metadata-Version: 1.0
Name: lmh
Version: 1.3
Summary: Local MathHub Utility (setup package)
Home-page: UNKNOWN
Author: The KWARC Group
Author-email: postmaster@kwarc.info
License: GPL
Platform: UNKNOWN
